pymilvus_simple/__init__.py
pymilvus_simple/simple_api.py
pymilvus_simple/simple_api_exceptions.py
pymilvus_simple-1.0.1.dist-info/METADATA
pymilvus_simple-1.0.1.dist-info/WHEEL
pymilvus_simple-1.0.1.dist-info/top_level.txt
pymilvus_simple-1.0.1.dist-info/RECORD
